app/main.py
app/models.py
app/searchManager.py
app/searchUtils.py
app/conf/basicConfig.py
app/conf/elasticConfig.py
app/conf/logConfig.py
app/routers/indexOperations.py
app/routers/searchOperations.py
lib_search_service-1.0.2.dist-info/LICENSE
lib_search_service-1.0.2.dist-info/METADATA
lib_search_service-1.0.2.dist-info/WHEEL
lib_search_service-1.0.2.dist-info/entry_points.txt
lib_search_service-1.0.2.dist-info/top_level.txt
lib_search_service-1.0.2.dist-info/RECORD
