Metadata-Version: 2.1
Name: lib-search-service
Version: 1.0.2
Summary: A search service enables efficient querying and retrieval of data, integrating with Elasticsearch to provide fast, scalable, and accurate search results across large datasets or systems.
Author-email: Lib-Go Author <admin@lib-go.com>
Project-URL: Homepage, https://github.com/Lib-Go-Website/Search-Service
Classifier: Intended Audience :: Developers
Classifier: Topic :: Software Development :: Build Tools
Classifier: Programming Language :: Python :: 3.8
Classifier: Programming Language :: Python :: 3.9
Classifier: Programming Language :: Python :: 3.10
Classifier: Programming Language :: Python :: 3.11
Classifier: Programming Language :: Python :: 3.12
Classifier: License :: OSI Approved :: MIT License
Classifier: Operating System :: OS Independent
Requires-Python: >=3.8
License-File: LICENSE
Requires-Dist: fastapi
Requires-Dist: uvicorn
